Metadata-Version: 2.1
Name: GroMaster
Version: 0.0.1
Summary: modbus lib for Growatt to get data and set data easily.
Home-page: https://github.com/yiwent/GroMaster
Author: Yiwentte Wong
Author-email: yiwentte@gmail.com
License: MIT
Platform: UNKNOWN
Classifier: License :: OSI Approved :: MIT License
Classifier: Programming Language :: Python
Classifier: Programming Language :: Python :: 3
Classifier: Programming Language :: Python :: 3.6
Classifier: Programming Language :: Python :: Implementation :: CPython
Classifier: Programming Language :: Python :: Implementation :: PyPy
Requires-Python: >=3.6.0
